torreable/__init__.py
torreable/server.py
torreable-0.2.0.dist-info/METADATA
torreable-0.2.0.dist-info/WHEEL
torreable-0.2.0.dist-info/entry_points.txt
torreable-0.2.0.dist-info/RECORD
