Metadata-Version: 2.4
Name: torreable
Version: 0.2.0
Summary: Publish static websites as Tor hidden services via MCP
Project-URL: Homepage, https://github.com/DOsinga/torreable
Project-URL: Repository, https://github.com/DOsinga/torreable
Author-email: Douwe Osinga <douwe.osinga@gmail.com>
License: MIT
Keywords: hidden-service,mcp,tor
Classifier: Development Status :: 3 - Alpha
Classifier: License :: OSI Approved :: MIT License
Classifier: Programming Language :: Python :: 3
Requires-Python: >=3.10
Requires-Dist: aiohttp
Requires-Dist: mcp
Requires-Dist: stem
